xecd_rates_client/XecdClient.py
xecd_rates_client/__init__.py
xecd_rates_client-1.0.0.dist-info/METADATA
xecd_rates_client-1.0.0.dist-info/RECORD
xecd_rates_client-1.0.0.dist-info/WHEEL
xecd_rates_client-1.0.0.dist-info/top_level.txt
xecd_rates_client-1.0.0.dist-info/zip-safe
