Metadata-Version: 2.1
Name: xecd-rates-client
Version: 1.0.0
Summary: XECD REST Client
Home-page: https://github.com/XenonLab/xecd-rates-client-python
Author: XE.com Inc. Development Team
Author-email: python@xe.com
License: UNKNOWN
Platform: UNKNOWN
Classifier: Programming Language :: Python :: 2
Classifier: Programming Language :: Python :: 3
Classifier: Intended Audience :: Developers
Classifier: License :: OSI Approved :: Mozilla Public License 2.0 (MPL 2.0)
Classifier: Operating System :: OS Independent
Classifier: Development Status :: 4 - Beta
